{
    "url": "https://www.slotjava.com/slot/bountypop/",
    "slug": "bountypop",
    "filename": "game_reviews/fix_log/bountypop.json",
    "html": "<!-- wp:image {\"align\":\"right\"} -->\n<figure class=\"wp-block-image alignright\"><img src=\"https://www.slotjava.com/wp-content/uploads/2023/06/Bountypop-Version-1-300x300.webp\" alt=\"BountyPop\"/></figure>\n<!-- /wp:image -->\n\n<h2>POPWINS FEATURE</h2>\n<p>Are you ready to pop your way to big wins? BountyPop has got you covered with its exciting PopWins function. Watch as each winning symbol explodes and is replaced by not one, but two symbols! It's like popping bubble wrap...only with coins!</p>\n<p></p>\n<p>The real game-changer, however, is the height of the reel that increases with each pop. With potential to expand up to 6 more symbols in the base game and a whopping 9 more symbols during free spins, you'll feel like you're on a never-ending stretchy toy. The only thing better than popping bubbles all day is getting rich while doing it, amirite?</p>\n<h2>Game Volatility and RTP</h2>\n<p>Is your heart racing yet? Because it should be. BountyPop is the slot game that will keep you on the edge of your seat with its high volatility. Just make sure you're not on the edge of a steep cliff, or you might fall off if you hit the jackpot.</p>\n<p>But seriously, BountyPop's high volatility means that it's not for the faint of heart. It's for the players who want to take risks and potentially reap huge rewards. And with an average RTP of 96%, those rewards can definitely be worth it!</p>\n<h2>WHEEL OF BETS</h2>\n<p>If you're looking for an online slot game that has a bit of everything, BountyPop may be worth a try. One of the unique features of this game is the Wheel of Bets, which is a sort of wheel of fortune that can really help boost your winnings. With each, win you get to spin the wheel and earn some free spins. Plus, it's just plain fun to spin that wheel and see where it lands! But beware, losing at the Wheel of Bets will send you plummeting back to the base game without any free spins, so it's definitely a gamble. </p>\n<p>Personally, I found myself spinning that Wheel of Bets more times than I would like to admit. There's something about the sound of the wheel spinning that just keeps me wanting more, and I know I'm not alone in that. So, if you're anything like me and love a good gamble, this game is definitely worth checking out. Just don't get too carried away, or you may find yourself spinning that wheel until you're out of money, and nobody wants that! </p>\n<h2>Graphics and Sound Design</h2>\n<p>Let's talk about BountyPop's graphics and sound design, shall we? While the pirate theme might suggest a swashbuckling visual and audio feast, the game's graphics are surprisingly simple. But hey, sometimes less is more, right? Even though the visuals aren't exactly groundbreaking, they still manage to create an engaging and enjoyable gaming experience.</p>\n<p>On the other hand, the sound design is a mixed bag. The background music hits the nail on the head and adds to the epic and adventurous feel of the game. It'll make you feel like you're aboard a pirate ship, searching for treasure on the high seas. However, the sound effects could be much better. They don't quite match the grandeur of the music and end up feeling lackluster and underwhelming.</p>\n<p>Despite that, the characters in the game are a real treat to look at. They evoke a sense of magic, mystery, and adventure. It's a shame the rest of the game's graphics don't quite match their level of creativity and detail. If only the entire game was as visually appealing as the characters, it would definitely be a treasure trove. Alas, that's not the case, and we'll just have to settle for the colorful and entertaining aspects that are present.</p>\n<h2>FAQ</h2>\n<h3>What is BountyPop?</h3>\n<p>BountyPop is a pirate-themed slot machine that offers high volatility and rich in bonuses.</p>\n<h3>What is the RTP of BountyPop?</h3>\n<p>The RTP of BountyPop is in the average of 96%.</p>\n<h3>What is the main feature of BountyPop?</h3>\n<p>The main feature of BountyPop is the PopWins function. Each winning symbol explodes and is replaced by two symbols that increase the height of the reel.</p>\n<h3>What activates the free spins in BountyPop?</h3>\n<p>Finding three or more scatter symbols (the mermaid) activates the free spins.</p>\n<h3>What is the 'Wheel of Bets' in BountyPop?</h3>\n<p>The 'Wheel of Bets' is a sort of wheel of fortune that, in the event of a win, will increase your free spins.</p>\n<h3>What happens if you lose at the 'Wheel of Bets' in BountyPop?</h3>\n<p>Losing at the 'Wheel of Bets' will return you to the base game without any free spins.</p>\n<h3>What is the 'Multiplier Wheel' in BountyPop?</h3>\n<p>The 'Multiplier Wheel' is activated when a reel reaches 6 symbols in height in the base game. Each level offers increasingly higher multipliers.</p>\n<h3>What are similar slots to BountyPop?</h3>\n<p>Wild Pirates, Pirate Gold Deluxe, and Octopus Treasure are similar slots to BountyPop.</p>\n<h2>What we like</h2>\n<ul>\n<li>PopWins feature</li>\n<li>Game volatility and RTP</li>\n<li>Multiplier wheel</li>\n<li>Wheel of Bets</li>\n</ul>\n<h2>What we don't like</h2>\n<ul>\n<li>Graphics and sound design</li>\n</ul>",
    "meta_title": "Play BountyPop Free - Review of the Exciting Online Slot",
    "meta_desc": "Read our review of BountyPop to discover the thrilling features and play for free.",
    "metas_fixed": true,
    "links_added": [
        "https://www.slotjava.com/slot/bountypop/",
        "https://www.slotjava.com/slot/octopus-treasure/",
        "https://www.slotjava.com/slot/wild-pirates/",
        "https://www.slotjava.com/online-slots/",
        "https://www.slotjava.com/slot/pirate-gold/",
        "https://www.slotjava.com/free-spins/"
    ],
    "new_html": "<!-- wp:image {\"align\":\"right\"} -->\n<figure class=\"wp-block-image alignright\"><img alt=\"BountyPop\" src=\"https://www.slotjava.com/wp-content/uploads/2023/06/Bountypop-Version-1-300x300.webp\"/></figure>\n<!-- /wp:image -->\n\n<p>Are you ready to pop your way to big wins? BountyPop has got you covered with its exciting PopWins function. Watch as each winning symbol explodes and is replaced by not one, but two symbols! It's like popping bubble wrap...only with coins!</p>\n<p></p>\n<p>The real game-changer, however, is the height of the reel that increases with each pop. With potential to expand up to 6 more symbols in the base game and a whopping 9 more symbols during <a href=\"https://www.slotjava.com/free-spins/\">free spins</a>, you'll feel like you're on a never-ending stretchy toy. The only thing better than popping bubbles all day is getting rich while doing it, amirite?</p>\n<h2>Game Volatility and RTP</h2>\n<p>Is your heart racing yet? Because it should be. BountyPop is the slot game that will keep you on the edge of your seat with its high volatility. Just make sure you're not on the edge of a steep cliff, or you might fall off if you hit the jackpot.</p>\n<p>But seriously, BountyPop's high volatility means that it's not for the faint of heart. It's for the players who want to take risks and potentially reap huge rewards. And with an average RTP of 96%, those rewards can definitely be worth it!</p>\n<h2>Wheel Of Bets</h2>\n<p>If you're looking for an <a href=\"https://www.slotjava.com/online-slots/\">online slot</a> game that has a bit of everything, BountyPop may be worth a try. One of the unique features of this game is the Wheel of Bets, which is a sort of wheel of fortune that can really help boost your winnings. With each, win you get to spin the wheel and earn some free spins. Plus, it's just plain fun to spin that wheel and see where it lands! But beware, losing at the Wheel of Bets will send you plummeting back to the base game without any free spins, so it's definitely a gamble. </p>\n<p>Personally, I found myself spinning that Wheel of Bets more times than I would like to admit. There's something about the sound of the wheel spinning that just keeps me wanting more, and I know I'm not alone in that. So, if you're anything like me and love a good gamble, this game is definitely worth checking out. Just don't get too carried away, or you may find yourself spinning that wheel until you're out of money, and nobody wants that! </p>\n<h2>Graphics and Sound Design</h2>\n<p>Let's talk about BountyPop's graphics and sound design, shall we? While the pirate theme might suggest a swashbuckling visual and audio feast, the game's graphics are surprisingly simple. But hey, sometimes less is more, right? Even though the visuals aren't exactly groundbreaking, they still manage to create an engaging and enjoyable gaming experience.</p>\n<p>On the other hand, the sound design is a mixed bag. The background music hits the nail on the head and adds to the epic and adventurous feel of the game. It'll make you feel like you're aboard a pirate ship, searching for treasure on the high seas. However, the sound effects could be much better. They don't quite match the grandeur of the music and end up feeling lackluster and underwhelming.</p>\n<p>Despite that, the characters in the game are a real treat to look at. They evoke a sense of magic, mystery, and adventure. It's a shame the rest of the game's graphics don't quite match their level of creativity and detail. If only the entire game was as visually appealing as the characters, it would definitely be a treasure trove. Alas, that's not the case, and we'll just have to settle for the colorful and entertaining aspects that are present.</p>\n<h2>FAQ</h2>\n<h3>What is BountyPop?</h3>\n<p>BountyPop is a pirate-themed slot machine that offers high volatility and rich in bonuses.</p>\n<h3>What is the RTP of BountyPop?</h3>\n<p>The RTP of BountyPop is in the average of 96%.</p>\n<h3>What is the main feature of BountyPop?</h3>\n<p>The main feature of BountyPop is the PopWins function. Each winning symbol explodes and is replaced by two symbols that increase the height of the reel.</p>\n<h3>What activates the free spins in BountyPop?</h3>\n<p>Finding three or more scatter symbols (the mermaid) activates the free spins.</p>\n<h3>What is the 'Wheel of Bets' in BountyPop?</h3>\n<p>The 'Wheel of Bets' is a sort of wheel of fortune that, in the event of a win, will increase your free spins.</p>\n<h3>What happens if you lose at the 'Wheel of Bets' in BountyPop?</h3>\n<p>Losing at the 'Wheel of Bets' will return you to the base game without any free spins.</p>\n<h3>What is the 'Multiplier Wheel' in BountyPop?</h3>\n<p>The 'Multiplier Wheel' is activated when a reel reaches 6 symbols in height in the base game. Each level offers increasingly higher multipliers.</p>\n<h3>What are similar slots to BountyPop?</h3>\n<p><a href=\"https://www.slotjava.com/slot/wild-pirates/\">Wild Pirates</a>, <a href=\"https://www.slotjava.com/slot/pirate-gold/\">Pirate Gold</a> Deluxe, and <a href=\"https://www.slotjava.com/slot/octopus-treasure/\">Octopus Treasure</a> are similar slots to BountyPop.</p>\n<h2>What we like</h2>\n<ul>\n<li>PopWins feature</li>\n<li>Game volatility and RTP</li>\n<li>Multiplier wheel</li>\n<li>Wheel of Bets</li>\n</ul>\n<h2>What we don't like</h2>\n<ul>\n<li>Graphics and sound design</li>\n</ul>",
    "meta_entry": "Title set: 'Play BountyPop Free - Review of the Exciting Online Slot' ### Meta set: 'Read our review of BountyPop to discover the thrilling features and play for free.'",
    "html_entry": "HTML inserted",
    "save_status": "Page Saved"
}